topsis_python/__init__.py
topsis_python-0.1.dist-info/LICENSE
topsis_python-0.1.dist-info/METADATA
topsis_python-0.1.dist-info/WHEEL
topsis_python-0.1.dist-info/top_level.txt
topsis_python-0.1.dist-info/RECORD
