Metadata-Version: 2.1
Name: topsis-python
Version: 0.1
Summary: topsis package in python
Home-page: https://github.com/rg3456/topsis_pck
Author: Ritik
Author-email: ritikgupta3008@gmail.com
License: UNKNOWN
Platform: UNKNOWN
Classifier: Programming Language :: Python :: 3
Classifier: License :: OSI Approved :: MIT License
Classifier: Operating System :: OS Independent
